arrayfire_wrapper/__init__.py
arrayfire_wrapper/_backend.py
arrayfire_wrapper/defines.py
arrayfire_wrapper/dtypes.py
arrayfire_wrapper/generated.txt
arrayfire_wrapper/generated_ignored.txt
arrayfire_wrapper/lib/__init__.py
arrayfire_wrapper/lib/_broadcast.py
arrayfire_wrapper/lib/_constants.py
arrayfire_wrapper/lib/_utility.py
arrayfire_wrapper/lib/array_layout.py
arrayfire_wrapper/lib/computer_vision/__init__.py
arrayfire_wrapper/lib/computer_vision/feature_descriptors.py
arrayfire_wrapper/lib/computer_vision/feature_detector.py
arrayfire_wrapper/lib/computer_vision/feature_matchers.py
arrayfire_wrapper/lib/computer_vision/template_matching.py
arrayfire_wrapper/lib/create_and_modify_array/__init__.py
arrayfire_wrapper/lib/create_and_modify_array/assignment_and_indexing/__init__.py
arrayfire_wrapper/lib/create_and_modify_array/assignment_and_indexing/_indexing.py
arrayfire_wrapper/lib/create_and_modify_array/assignment_and_indexing/assign.py
arrayfire_wrapper/lib/create_and_modify_array/assignment_and_indexing/index.py
arrayfire_wrapper/lib/create_and_modify_array/assignment_and_indexing/lookup.py
arrayfire_wrapper/lib/create_and_modify_array/create_array/__init__.py
arrayfire_wrapper/lib/create_and_modify_array/create_array/constant.py
arrayfire_wrapper/lib/create_and_modify_array/create_array/diag.py
arrayfire_wrapper/lib/create_and_modify_array/create_array/identity.py
arrayfire_wrapper/lib/create_and_modify_array/create_array/iota.py
arrayfire_wrapper/lib/create_and_modify_array/create_array/lower.py
arrayfire_wrapper/lib/create_and_modify_array/create_array/pad.py
arrayfire_wrapper/lib/create_and_modify_array/create_array/random_number_generation.py
arrayfire_wrapper/lib/create_and_modify_array/create_array/range.py
arrayfire_wrapper/lib/create_and_modify_array/create_array/upper.py
arrayfire_wrapper/lib/create_and_modify_array/helper_functions.py
arrayfire_wrapper/lib/create_and_modify_array/manage_array.py
arrayfire_binary_python_wrapper-0.8.0.dist-info/METADATA
arrayfire_binary_python_wrapper-0.8.0.dist-info/WHEEL
arrayfire_binary_python_wrapper-0.8.0.dist-info/licenses/LICENSE
arrayfire_binary_python_wrapper-0.8.0.dist-info/RECORD
