Metadata-Version: 2.2
Name: arrayfire-binary-python-wrapper
Version: 0.8.0
Summary: ArrayFire Python Wrapper
Keywords: arrayfire,c,python,wrapper,parallel computing,gpu,cpu,opencl,oneapi
Author-Email: ArrayFire <technical@arrayfire.com>, Anton Chernyatevich <chernyatevich.a@gmail.com>
Maintainer-Email: ArrayFire <technical@arrayfire.com>
License: BSD 3-Clause License
Classifier: Intended Audience :: Science/Research
Classifier: Intended Audience :: Developers
Classifier: Development Status :: 4 - Beta
Classifier: License :: OSI Approved :: BSD License
Classifier: Programming Language :: Python
Classifier: Programming Language :: Python :: 3
Classifier: Programming Language :: Python :: 3.10
Classifier: Topic :: Scientific/Engineering
Classifier: Topic :: Scientific/Engineering :: Artificial Intelligence
Classifier: Topic :: Scientific/Engineering :: Information Analysis
Classifier: Topic :: Scientific/Engineering :: Mathematics
Classifier: Topic :: Software Development :: Libraries
Project-URL: Website, http://arrayfire.com
Project-URL: General Documentation, https://arrayfire.org/docs/index.htm
Requires-Python: >=3.10
